{"0": {"pos": [236, 21012, 7177], "neg": []}, "1": {"pos": [27357, 3633, 3965], "neg": []}, "2": {"pos": [2213, 32440, 257], "neg": []}, "3": {"pos": [24084, 24208, 24244], "neg": []}, "4": {"pos": [5694, 4829, 6016], "neg": []}, "5": {"pos": [18216, 18437, 16498], "neg": []}, "6": {"pos": [8478, 8557, 9003], "neg": []}, "7": {"pos": [28002, 28308], "neg": []}, "8": {"pos": [14279, 14149, 14077], "neg": []}, "9": {"pos": [8320, 26697, 26521], "neg": []}, "10": {"pos": [4962, 27253, 4836], "neg": []}, "11": {"pos": [14678, 58, 29769], "neg": []}, "12": {"pos": [2859, 2868, 2729], "neg": []}, "13": {"pos": [21048, 11269, 20956], "neg": []}, "14": {"pos": [11124, 4326, 10858], "neg": []}, "15": {"pos": [17370, 17226, 2399], "neg": []}, "16": {"pos": [16564, 16772, 18249], "neg": []}, "17": {"pos": [22612, 1723, 1713], "neg": []}, "18": {"pos": [31333, 22888, 22818], "neg": []}, "19": {"pos": [28780, 11356, 22837], "neg": []}, "20": {"pos": [10893, 13981, 10681], "neg": []}, "21": {"pos": [12992, 26389, 13106], "neg": []}, "22": {"pos": [21798, 21826, 21736], "neg": []}, "23": {"pos": [313, 31439, 27117], "neg": []}, "24": {"pos": [20877, 3781, 28563], "neg": []}, "25": {"pos": [12570, 32282, 3169], "neg": []}, "26": {"pos": [9974, 9641, 9828], "neg": []}, "27": {"pos": [32246, 17827, 17521], "neg": []}, "28": {"pos": [11500, 30935, 12488], "neg": []}, "29": {"pos": [28357, 22397, 22459], "neg": []}, "30": {"pos": [31537, 11900, 11909], "neg": []}, "31": {"pos": [15735, 20090, 15596], "neg": []}, "32": {"pos": [21250, 20776, 1342], "neg": []}, "33": {"pos": [30281, 30325, 30355], "neg": []}, "34": {"pos": [5279, 5745, 6279], "neg": []}, "35": {"pos": [4309, 4320, 32441], "neg": []}, "36": {"pos": [5701, 21666, 31285], "neg": []}, "37": {"pos": [11292, 8717, 28261], "neg": []}, "38": {"pos": [2066, 2386, 1112], "neg": []}, "39": {"pos": [15662, 15506, 30194], "neg": []}, "40": {"pos": [16967, 15840, 10802], "neg": []}, "41": {"pos": [26302, 26089, 26284], "neg": []}, "42": {"pos": [23098, 23194, 22037], "neg": []}, "43": {"pos": [9748, 20242, 13302], "neg": []}, "44": {"pos": [6566, 31936, 6532], "neg": []}, "45": {"pos": [22110, 4663, 6172], "neg": []}, "46": {"pos": [16916, 16091, 31619], "neg": []}, "47": {"pos": [1705, 16224, 20208], "neg": []}, "48": {"pos": [15885, 29384, 16040], "neg": []}, "49": {"pos": [6436, 6271, 26277], "neg": []}, "50": {"pos": [27662, 27573, 27595], "neg": []}, "51": {"pos": [4311, 25351, 26727], "neg": []}, "52": {"pos": [26861, 14764, 22258], "neg": []}, "53": {"pos": [26141, 5407, 30069], "neg": []}, "54": {"pos": [32347, 32461, 20988], "neg": []}, "55": {"pos": [19901, 20570, 19903], "neg": []}, "56": {"pos": [20328, 19153, 27674], "neg": []}, "57": {"pos": [26166, 25411, 21911], "neg": []}, "58": {"pos": [22314, 22526, 22412], "neg": []}, "59": {"pos": [19318, 18971, 19177], "neg": []}, "60": {"pos": [15609, 25960, 18432], "neg": []}, "61": {"pos": [21486, 21509, 21471], "neg": []}, "62": {"pos": [28963, 4952, 21168], "neg": []}, "63": {"pos": [21318, 21411, 21329], "neg": []}, "64": {"pos": [19823, 31889, 5931], "neg": []}, "65": {"pos": [22055, 22056, 22424], "neg": []}, "66": {"pos": [2557, 23009, 22991], "neg": []}, "67": {"pos": [14036, 13460, 14216], "neg": []}, "68": {"pos": [21452, 19075, 19014], "neg": []}, "69": {"pos": [23021, 26436, 29217], "neg": []}, "70": {"pos": [10492, 13398, 28859], "neg": []}, "71": {"pos": [3225, 12876, 28594], "neg": []}, "72": {"pos": [5808, 13275, 8549], "neg": []}, "73": {"pos": [13807, 3105, 30658], "neg": []}, "74": {"pos": [14009, 1890, 20195], "neg": []}, "75": {"pos": [11786, 11299, 25839], "neg": []}, "76": {"pos": [4486, 11474, 11557], "neg": []}, "77": {"pos": [8652, 3697, 12454], "neg": []}, "78": {"pos": [25854, 25905, 16254], "neg": []}, "79": {"pos": [29887, 21923, 26991], "neg": []}, "80": {"pos": [4505, 18836, 18577], "neg": []}, "81": {"pos": [21412, 15065, 8773], "neg": []}, "82": {"pos": [22606, 20666, 29665], "neg": []}, "83": {"pos": [22852, 2246, 1989], "neg": []}, "84": {"pos": [6315, 32592, 14205], "neg": []}, "85": {"pos": [3843, 11307, 1318], "neg": []}, "86": {"pos": [2778, 976, 20711], "neg": []}, "87": {"pos": [32384, 4961, 6709], "neg": []}, "88": {"pos": [1125, 18540, 11422], "neg": []}, "89": {"pos": [18860, 9300, 8013], "neg": []}, "90": {"pos": [31042, 10309, 10326], "neg": []}, "91": {"pos": [22187, 29313, 28320], "neg": []}, "92": {"pos": [5042, 1205, 19085], "neg": []}, "93": {"pos": [10572, 15207, 30702], "neg": []}, "94": {"pos": [18854, 3168, 4784], "neg": []}, "95": {"pos": [11225, 26555, 16884], "neg": []}, "96": {"pos": [5517, 29134, 29228], "neg": []}, "97": {"pos": [12468, 5744, 19514], "neg": []}, "98": {"pos": [28382, 8786, 31154], "neg": []}, "99": {"pos": [13463, 18791, 28436], "neg": []}}