{"0": {"pos": [24434, 24646, 23406], "neg": []}, "1": {"pos": [12525, 21165, 12343], "neg": []}, "2": {"pos": [30360, 1838, 6117], "neg": []}, "3": {"pos": [1921, 2588, 2509], "neg": []}, "4": {"pos": [28514, 2598, 1210], "neg": []}, "5": {"pos": [5108, 27123, 27899], "neg": []}, "6": {"pos": [18128, 16299, 16875], "neg": []}, "7": {"pos": [31136, 27950, 26672], "neg": []}, "8": {"pos": [29862, 30627, 6400], "neg": []}, "9": {"pos": [1425, 8407, 1509], "neg": []}, "10": {"pos": [30238, 26274, 27007], "neg": []}, "11": {"pos": [13857, 14114, 13463], "neg": []}, "12": {"pos": [27972, 28006, 28020], "neg": []}, "13": {"pos": [32133, 2828, 4596], "neg": []}, "14": {"pos": [16364, 30316, 30371], "neg": []}, "15": {"pos": [19414, 17979, 23944], "neg": []}, "16": {"pos": [17715, 6054, 17486], "neg": []}, "17": {"pos": [5320, 2196, 2168], "neg": []}, "18": {"pos": [27144, 27109, 1062], "neg": []}, "19": {"pos": [18641, 7361, 10893], "neg": []}, "20": {"pos": [16934, 23172, 17137], "neg": []}, "21": {"pos": [22190, 22054, 23004], "neg": []}, "22": {"pos": [1011, 1381, 459], "neg": []}, "23": {"pos": [13751, 13905, 14559], "neg": []}, "24": {"pos": [32484, 31407, 30887], "neg": []}, "25": {"pos": [8271, 8091, 8719], "neg": []}, "26": {"pos": [28538, 17854, 30185], "neg": []}, "27": {"pos": [28284, 28147, 29919], "neg": []}, "28": {"pos": [4919, 5896, 4983], "neg": []}, "29": {"pos": [3379, 25680, 3823], "neg": []}, "30": {"pos": [21531, 4990, 3154], "neg": []}, "31": {"pos": [15569, 19786, 22888], "neg": []}, "32": {"pos": [29558, 29688, 16410], "neg": []}, "33": {"pos": [14754, 15106, 23221], "neg": []}, "34": {"pos": [4141, 18868, 3984], "neg": []}, "35": {"pos": [6215, 11973, 4726], "neg": []}, "36": {"pos": [24597, 24963, 25233], "neg": []}, "37": {"pos": [19280, 19196, 19187], "neg": []}, "38": {"pos": [9970, 13569, 9401], "neg": []}, "39": {"pos": [20006, 15371, 2245], "neg": []}, "40": {"pos": [2137, 6554, 1056], "neg": []}, "41": {"pos": [10332, 172, 25510], "neg": []}, "42": {"pos": [22722, 11723, 10446], "neg": []}, "43": {"pos": [9223, 4420, 9292], "neg": []}, "44": {"pos": [32070, 9590, 17388], "neg": []}, "45": {"pos": [6860, 12224, 1280], "neg": []}, "46": {"pos": [21782, 30677, 7576], "neg": []}, "47": {"pos": [17241, 16779, 11330], "neg": []}, "48": {"pos": [13078, 13102, 12811], "neg": []}, "49": {"pos": [31107, 11189, 13695], "neg": []}}